graph_simulator.cpython-312-darwin.so
graph_simulator-0.2.9.dist-info/METADATA
graph_simulator-0.2.9.dist-info/WHEEL
graph_simulator-0.2.9.dist-info/licenses/LICENSE
graph_simulator-0.2.9.dist-info/RECORD
