Metadata-Version: 2.2
Name: graph_simulator
Version: 0.2.9
Summary: A tool to simulate from graphs
Author-Email: "Joakim B. Andersen" <blach.andersen@gmail.com>
Requires-Python: >=3.9
Requires-Dist: pybind11>=2.13.6
